[{
    "hour_interval": "9:00 pm - 10:00 am",
    "part_number": "2hj11111893k234",
    "ideal": "100",
    "target_pcs": "75",
    "actual_pcs": "66",
    "cumulative_target_pcs": "75",
    "cumulative_pcs": "77",
    "timelost": "10",
    "timelost_reason_code": "124",
    "actions_comments": "I found a defect, have to speak to a supervisor before proceeding",
    "oper_id": "SW",
    "superv_id": "DS",
    "order_id": "1312fgdfe325342"
}, {
    "hour_interval": "10:00 pm - 11:00 am",
    "part_number": "2hj11111893k234",
    "ideal": "",
    "target_pcs": "75",
    "actual_pcs": "72",
    "cumulative_target_pcs": "75",
    "cumulative_pcs": "77",
    "timelost": "10",
    "timelost_reason_code": "124",
    "actions_comments": "I found a defect, have to speak to a supervisor before proceeding",
    "oper_id": "SW",
    "superv_id": "DS"
}, {
    "hour_interval": "11:00 pm - 12:00 am",
    "part_number": "2hj4idh5893k234",
    "ideal": "",
    "target_pcs": "75",
    "actual_pcs": "55",
    "cumulative_target_pcs": "75",
    "cumulative_pcs": "77",
    "timelost": "10",
    "timelost_reason_code": "124",
    "actions_comments": "Something Happened Here",
    "oper_id": "SW",
    "superv_id": "DS"
}, {
    "hour_interval": "12:00 am - 01:00 pm",
    "part_number": "49242j438f2413k",
    "ideal": "",
    "target_pcs": "72",
    "actual_pcs": "71",
    "cumulative_target_pcs": "148",
    "cumulative_pcs": "148",
    "timelost": "08",
    "timelost_reason_code": "124",
    "actions_comments": "Woops Something Broke",
    "oper_id": "RF",
    "superv_id": "DF"
}, {
    "hour_interval": "11:00 pm - 12:00 am",
    "part_number": "0493847jkd38frj2",
    "ideal": "100",
    "target_pcs": "74",
    "actual_pcs": "45",
    "cumulative_target_pcs": "222",
    "cumulative_pcs": "220",
    "timelost": "",
    "timelost_reason_code": "124",
    "actions_comments": "",
    "oper_id": "JS",
    "superv_id": "AV"
}, {
    "hour_interval": "01:00 am - 02:00 pm",
    "part_number": "294jdl4855349dd",
    "ideal": "100",
    "target_pcs": "72",
    "actual_pcs": "72",
    "cumulative_target_pcs": "294",
    "cumulative_pcs": null,
    "timelost": "",
    "timelost_reason_code": "124",
    "actions_comments": "It seems we have a situation over here",
    "oper_id": "GA",
    "superv_id": "AV"
}, {
    "hour_interval": "02:00 am - 03:00 pm",
    "part_number": "al3924850284234",
    "ideal": "100",
    "target_pcs": "70",
    "actual_pcs": "70",
    "cumulative_target_pcs": "364",
    "cumulative_pcs": "360",
    "timelost": "02",
    "timelost_reason_code": "124",
    "actions_comments": "",
    "oper_id": "BM",
    "superv_id": "AV"
}, {
    "hour_interval": "02:00 am - 03:00 pm",
    "part_number": "al39233333334234",
    "ideal": "100",
    "target_pcs": "70",
    "actual_pcs": "70",
    "cumulative_target_pcs": "364",
    "cumulative_pcs": "360",
    "timelost": "02",
    "timelost_reason_code": "124",
    "actions_comments": "",
    "oper_id": "BM",
    "superv_id": "AV"
}, {
    "hour_interval": "02:00 am - 03:00 pm",
    "part_number": "al39555555584234",
    "ideal": "100",
    "target_pcs": "70",
    "actual_pcs": "70",
    "cumulative_target_pcs": "364",
    "cumulative_pcs": "360",
    "timelost": "02",
    "timelost_reason_code": "124",
    "actions_comments": "There is a raccoon stuck in the fan",
    "oper_id": "BM",
    "superv_id": "AV"
}, {
    "hour_interval": "03:00 am - 04:00 pm",
    "part_number": "al3924850111211",
    "ideal": "100",
    "target_pcs": "75",
    "actual_pcs": "78",
    "cumulative_target_pcs": "439",
    "cumulative_pcs": "430",
    "timelost": "02",
    "timelost_reason_code": "124",
    "actions_comments": "",
    "oper_id": "BM",
    "superv_id": "AV"
}, {
    "hour_interval": "04:00 am - 05:00 pm",
    "part_number": "al3924850111211",
    "ideal": "101",
    "target_pcs": "75",
    "actual_pcs": "87",
    "cumulative_target_pcs": "439",
    "cumulative_pcs": "430",
    "timelost": "02",
    "timelost_reason_code": "124",
    "actions_comments": "",
    "oper_id": "BM",
    "superv_id": "AV"
}]